Jacks-0.1.0.dist-info/METADATA
Jacks-0.1.0.dist-info/RECORD
Jacks-0.1.0.dist-info/WHEEL
Jacks-0.1.0.dist-info/top_level.txt
jacks/__init__.py
jacks/card.py
jacks/deck.py
jacks/evaluator.py
