Metadata-Version: 2.1
Name: Jacks
Version: 0.1.0
Summary: Basic Commands for Poker
Home-page: https://github.com/Cheran-Senthil/Jacks
Author: Cheran and Mukundan
Author-email: UNKNOWN
License: Apache License 2.0
Platform: UNKNOWN
Requires-Dist: six
Requires-Dist: termcolor
